MANIFEST.in
README.rst
requirements.txt
setup.py
web_rich_object/__init__.py
web_rich_object/api.py
web_rich_object/functional_tests.py
web_rich_object/utils.py
web_rich_object.egg-info/PKG-INFO
web_rich_object.egg-info/SOURCES.txt
web_rich_object.egg-info/dependency_links.txt
web_rich_object.egg-info/requires.txt
web_rich_object.egg-info/top_level.txt
web_rich_object/tests/__init__.py
web_rich_object/tests/factories.py
web_rich_object/tests/test_common.py
web_rich_object/tests/test_html.py
web_rich_object/tests/test_image.py
web_rich_object/tests/test_pdf.py
web_rich_object/tests/utils.py