Metadata-Version: 1.1
Name: web-rich-object
Version: 0.3.1
Summary: Web rich object handler
Home-page: https://github.com/ZuluPro/web-rich-object
Author: Anthony Monthe (ZuluPro)
Author-email: anthony.monthe@gmail.com
License: BSD
Keywords: web rich object,opengraph,facebook,web,twitter
Platform: UNKNOWN
Classifier: Development Status :: 3 - Alpha
Classifier: Intended Audience :: Developers
Classifier: License :: OSI Approved :: BSD License
Classifier: Operating System :: OS Independent
Classifier: Programming Language :: Python
Classifier: Programming Language :: Python :: 2.7
Classifier: Programming Language :: Python :: 3.3
Classifier: Programming Language :: Python :: 3.4
Classifier: Programming Language :: Python :: 3.5
Classifier: Topic :: Software Development
Classifier: Topic :: Software Development :: Libraries
Classifier: Topic :: Software Development :: Libraries :: Python Modules
